{
	"id": "256e15e3-a352-45a8-8d86-193f41d5590c",
	"name": "ASK_QA",
	"values": [
		{
			"key": "baseUrl",
			"value": "http://ask-qa.portnov.com/api/v1",
			"type": "default",
			"enabled": true
		},
		{
			"key": "teacherToken",
			"value": "eyJhbGciOiJIUzI1NiIsInR5cCI6IkpXVCJ9.eyJlbWFpbCI6ImR3ODI0N0BnZXJtZW1lbWJyYW5sYXIuY29tIiwiaWF0IjoxNjkwNzgxMDcyLCJleHAiOjE2OTA4Njc0NzJ9.bRc53V2BW_Q2Piy8EdV0dkArN3Fhk5TS5G7vS_K450Y",
			"type": "default",
			"enabled": true
		},
		{
			"key": "studentToken",
			"value": "eyJhbGciOiJIUzI1NiIsInR5cCI6IkpXVCJ9.eyJlbWFpbCI6ImZpcmUxNDhoMjVAbXJzZnMuY29tIiwiaWF0IjoxNjkwNzgyNDc2LCJleHAiOjE2OTA4Njg4NzZ9.xtKn8UoOFLut1Gtr1VEyGO1ph-zNCCrCwNlIT8_1YF4",
			"type": "default",
			"enabled": true
		},
		{
			"key": "studentId",
			"value": "",
			"type": "default",
			"enabled": true
		},
		{
			"key": "quizId",
			"value": "",
			"type": "default",
			"enabled": true
		},
		{
			"key": "assignmentId",
			"value": "",
			"type": "default",
			"enabled": true
		},
		{
			"key": "assignmentGroupID",
			"value": "",
			"type": "default",
			"enabled": true
		},
		{
			"key": "activationCode",
			"value": "",
			"type": "any",
			"enabled": true
		}
	],
	"_postman_variable_scope": "environment",
	"_postman_exported_at": "2023-08-07T05:18:44.174Z",
	"_postman_exported_using": "Postman/10.16.4"
}